dependency_resolution/__init__.py
dependency_resolution/auto_wired_cache.py
dependency_resolution/provider_cache.py
dependency_resolution-0.2.2.dist-info/LICENSE
dependency_resolution-0.2.2.dist-info/WHEEL
dependency_resolution-0.2.2.dist-info/METADATA
dependency_resolution-0.2.2.dist-info/RECORD
