Metadata-Version: 2.1
Name: dependency-resolution
Version: 0.2.2
Summary: A simple dependency resolution library using container concepts
License: MIT
Keywords: dependency,resolution,injection
Author: Saroopashree K
Author-email: saroopa25@gmail.com
Requires-Python: >=3.8.0,<4.0.0
Classifier: License :: OSI Approved :: MIT License
Classifier: Programming Language :: Python :: 3
Classifier: Programming Language :: Python :: 3.8
Classifier: Programming Language :: Python :: 3.9
Classifier: Programming Language :: Python :: 3.10
Classifier: Programming Language :: Python :: 3.11
